attention_tensorflow_mesh/__init__.py
attention_tensorflow_mesh/attention_tensorflow_mesh.py
attention_tensorflow_mesh-0.0.2.dist-info/LICENSE
attention_tensorflow_mesh-0.0.2.dist-info/METADATA
attention_tensorflow_mesh-0.0.2.dist-info/WHEEL
attention_tensorflow_mesh-0.0.2.dist-info/top_level.txt
attention_tensorflow_mesh-0.0.2.dist-info/RECORD
